direct_neural_biasing-1.0.7.dist-info/METADATA
direct_neural_biasing-1.0.7.dist-info/WHEEL
direct_neural_biasing/__init__.py
direct_neural_biasing/direct_neural_biasing.cp310-win_amd64.pyd
direct_neural_biasing-1.0.7.dist-info/RECORD
