Metadata-Version: 2.1
Name: direct-neural-biasing
Version: 1.0.7
Author: Daniel Humphries <d.humphries@ucl.ac.uk>
Author-email: Daniel Humphries <d.humphries@ucl.ac.uk>
License: CC-BY-NC-4.0
